qpSWIFT_sparse_bindings.cpython-312-x86_64-linux-gnu.so
qpswift_sparse_bindings-1.0.2.dist-info/METADATA
qpswift_sparse_bindings-1.0.2.dist-info/WHEEL
qpswift_sparse_bindings-1.0.2.dist-info/top_level.txt
qpswift_sparse_bindings-1.0.2.dist-info/RECORD
