Metadata-Version: 2.1
Name: qpSWIFT_sparse_bindings
Version: 1.0.2
Summary: Custom sparse python bindings for the qpSWIFT solver
Home-page: https://github.com/SemRoCo/qpSWIFT
Author: Simon Stelter
License: GPLv3
Classifier: Development Status :: 5 - Production/Stable
Classifier: License :: OSI Approved :: GNU General Public License v3 (GPLv3)
Classifier: Operating System :: POSIX :: Linux
Classifier: Intended Audience :: Science/Research
Classifier: Programming Language :: Python
Classifier: Programming Language :: Python :: 3.8
Classifier: Programming Language :: Python :: 3.9
Classifier: Programming Language :: Python :: 3.10
Classifier: Programming Language :: Python :: 3.11
Classifier: Programming Language :: Python :: 3.12
Requires-Python: >=3.8, <3.13
Requires-Dist: numpy
Requires-Dist: scipy
Requires-Dist: pybind11
